herta_villa_sdk-0.9.0.dist-info/METADATA
herta_villa_sdk-0.9.0.dist-info/WHEEL
herta_villa_sdk-0.9.0.dist-info/licenses/LICENSE
hertavilla/__init__.py
hertavilla/apis/__init__.py
hertavilla/apis/audit.py
hertavilla/apis/auth.py
hertavilla/apis/emoticon.py
hertavilla/apis/img.py
hertavilla/apis/internal.py
hertavilla/apis/member.py
hertavilla/apis/message.py
hertavilla/apis/role.py
hertavilla/apis/room.py
hertavilla/apis/villa.py
hertavilla/apis/websocket.py
hertavilla/bot.py
hertavilla/event.py
hertavilla/exception.py
hertavilla/match.py
hertavilla/message/__init__.py
hertavilla/message/chain.py
hertavilla/message/component.py
hertavilla/message/image.py
hertavilla/message/internal.py
hertavilla/message/post.py
hertavilla/message/text.py
hertavilla/model.py
hertavilla/server/__init__.py
hertavilla/server/_lifespan.py
hertavilla/server/aiohttp.py
hertavilla/server/fastapi.py
hertavilla/server/internal.py
hertavilla/server/loop.py
hertavilla/typing.py
hertavilla/utils.py
hertavilla/version.py
hertavilla/ws/__init__.py
hertavilla/ws/connection.py
hertavilla/ws/package.py
hertavilla/ws/payload.py
hertavilla/ws/pb/command_pb2.py
hertavilla/ws/pb/command_pb2.pyi
hertavilla/ws/pb/model_pb2.py
hertavilla/ws/pb/model_pb2.pyi
hertavilla/ws/pb/robot_event_message_pb2.py
hertavilla/ws/pb/robot_event_message_pb2.pyi
hertavilla/ws/types.py
herta_villa_sdk-0.9.0.dist-info/RECORD
