Metadata-Version: 2.1
Name: herta-villa-sdk
Version: 0.9.0
Summary: 大别野「黑塔」Python SDK
Keywords: mihoyo miyoushe bot villa
Author-Email: MingxuanGame <MingxuanGame@outlook.com>
License: MIT
Project-URL: Homepage, https://github.com/Herta-villa/Herta-villa-SDK
Project-URL: Documentation, https://github.com/Herta-villa/Herta-villa-SDK
Project-URL: Repository, https://github.com/Herta-villa/Herta-villa-SDK
Project-URL: Bug tracker, https://github.com/Herta-villa/Herta-villa-SDK/issues
Requires-Python: >=3.8
Requires-Dist: aiohttp>=3.8.4
Requires-Dist: pydantic<2.0,>=1.10.8
Requires-Dist: rsa>=4.9
Requires-Dist: fastapi>=0.100.0; extra == "fastapi"
Requires-Dist: uvicorn>=0.22.0; extra == "fastapi"
Requires-Dist: protobuf>=4.25.1; extra == "ws"
Provides-Extra: fastapi
Provides-Extra: ws
